LICENSE
kafka_overwatch/__init__.py
kafka_overwatch/aws_helpers/__init__.py
kafka_overwatch/aws_helpers/kafka_client_secrets.py
kafka_overwatch/aws_helpers/s3.py
kafka_overwatch/cli/__init__.py
kafka_overwatch/cli/schema_registry_restore.py
kafka_overwatch/common/__init__.py
kafka_overwatch/config/__init__.py
kafka_overwatch/config/config.py
kafka_overwatch/config/logging.py
kafka_overwatch/config/threads_settings.py
kafka_overwatch/kafka_resources/__init__.py
kafka_overwatch/kafka_resources/groups.py
kafka_overwatch/kafka_resources/topics.py
kafka_overwatch/monitoring/__init__.py
kafka_overwatch/monitoring/prometheus.py
kafka_overwatch/notifications/__init__.py
kafka_overwatch/notifications/aws_sns/__init__.py
kafka_overwatch/notifications/aws_sns/usage_report/__init__.py
kafka_overwatch/notifications/aws_sns/usage_report/default.j2
kafka_overwatch/notifications/aws_sns/usage_report/email.j2
kafka_overwatch/overwatch.py
kafka_overwatch/overwatch_resources/__init__.py
kafka_overwatch/overwatch_resources/clusters.py
kafka_overwatch/overwatch_resources/groups.py
kafka_overwatch/overwatch_resources/schema_registry/__init__.py
kafka_overwatch/overwatch_resources/schema_registry/schema.py
kafka_overwatch/overwatch_resources/schema_registry/schemas_restore.py
kafka_overwatch/overwatch_resources/schema_registry/subject.py
kafka_overwatch/overwatch_resources/topics.py
kafka_overwatch/processing/__init__.py
kafka_overwatch/processing/clusters.py
kafka_overwatch/processing/schema_registries.py
kafka_overwatch/processing/signals.py
kafka_overwatch/reporting/__init__.py
kafka_overwatch/reporting/governance/__init__.py
kafka_overwatch/reporting/governance/consumer_groups_naming_convention.py
kafka_overwatch/reporting/governance/topic_naming_convention.py
kafka_overwatch/reporting/schema_registry.py
kafka_overwatch/reporting/tools.py
kafka_overwatch/reporting/topics.py
kafka_overwatch/specs/__init__.py
kafka_overwatch/specs/config.json
kafka_overwatch/specs/config.py
kafka_overwatch-0.5.0.post0.dist-info/AUTHORS.rst
kafka_overwatch-0.5.0.post0.dist-info/LICENSE
kafka_overwatch-0.5.0.post0.dist-info/METADATA
kafka_overwatch-0.5.0.post0.dist-info/WHEEL
kafka_overwatch-0.5.0.post0.dist-info/entry_points.txt
kafka_overwatch-0.5.0.post0.dist-info/RECORD
