Metadata-Version: 2.1
Name: kafka-overwatch
Version: 0.5.0.post0
Summary: Continuously monitors Kafka cluster topics & consumer groups
License: MPL-2.0
Keywords: kafka,monitoring,reporting,usage-analysis,cost-savings
Author: John "Preston" Mille
Author-email: john@ews-network.net
Maintainer: John "Preston" Mille
Maintainer-email: john@ews-network.net
Requires-Python: >=3.10,<4.0
Classifier: Development Status :: 4 - Beta
Classifier: Intended Audience :: Developers
Classifier: Intended Audience :: Information Technology
Classifier: Intended Audience :: System Administrators
Classifier: License :: OSI Approved
Classifier: License :: OSI Approved :: Mozilla Public License 2.0 (MPL 2.0)
Classifier: Natural Language :: English
Classifier: Programming Language :: Python :: 3
Classifier: Programming Language :: Python :: 3.10
Classifier: Programming Language :: Python :: 3.11
Classifier: Programming Language :: Python :: 3.12
Requires-Dist: aws-cfn-custom-resource-resolve-parser (>=0.3,<0.4)
Requires-Dist: aws-embedded-metrics (>=3.2.0,<4.0.0)
Requires-Dist: aws-msk-iam-sasl-signer-python (>=1.0.0,<2.0.0)
Requires-Dist: boto3 (>=1.26,<2.0)
Requires-Dist: codeguru-profiler-agent (>=1.2.4,<2.0.0)
Requires-Dist: compose-x-common (>=1.4,<2.0)
Requires-Dist: confluent-kafka (>=2.3.0,<3.0.0)
Requires-Dist: cryptography (>=42.0.5,<43.0.0)
Requires-Dist: dacite (>=1.8.1,<2.0.0)
Requires-Dist: importlib-resources (>=6.1.1,<7.0.0)
Requires-Dist: jinja2 (>=3.1.2,<4.0.0)
Requires-Dist: jsonschema (>=4.20.0,<5.0.0)
Requires-Dist: kafka-schema-registry-admin (>=0.5)
Requires-Dist: pandas (>=2.1.4,<3.0.0)
Requires-Dist: prometheus-client (>=0.20,<0.21)
Requires-Dist: pyyaml (>=6.0.1,<7.0.0)
Requires-Dist: retry2 (>=0.9.5,<0.10.0)
Project-URL: Bug Tracker, https://github.com/JohnPreston/kafka-overwatch/issues
